odoo/addons/partner_contact_external_ref/LICENSE
odoo/addons/partner_contact_external_ref/README.rst
odoo/addons/partner_contact_external_ref/__init__.py
odoo/addons/partner_contact_external_ref/__manifest__.py
odoo/addons/partner_contact_external_ref/images/screen.png
odoo/addons/partner_contact_external_ref/models/__init__.py
odoo/addons/partner_contact_external_ref/models/res_partner.py
odoo/addons/partner_contact_external_ref/readme/CONTRIBUTORS.md
odoo/addons/partner_contact_external_ref/readme/DESCRIPTION.md
odoo/addons/partner_contact_external_ref/readme/USAGE.md
odoo/addons/partner_contact_external_ref/static/description/icon.png
odoo/addons/partner_contact_external_ref/static/description/index.html
odoo/addons/partner_contact_external_ref/views/res_partner.xml
odoo_addon_partner_contact_external_ref-18.0.1.0.0.dist-info/METADATA
odoo_addon_partner_contact_external_ref-18.0.1.0.0.dist-info/WHEEL
odoo_addon_partner_contact_external_ref-18.0.1.0.0.dist-info/top_level.txt
odoo_addon_partner_contact_external_ref-18.0.1.0.0.dist-info/RECORD
